AUTHORS
LICENSE
MANIFEST.in
README.md
setup.cfg
setup.py
cam/__init__.py
cam/__main__.py
cam/cli.py
cam/command.py
cam/enums.py
cam/errors.py
cam/hacks.py
cam/interpreter.py
cam/source.py
cam/sysinfo.py
cam.egg-info/PKG-INFO
cam.egg-info/SOURCES.txt
cam.egg-info/dependency_links.txt
cam.egg-info/entry_points.txt
cam.egg-info/requires.txt
cam.egg-info/top_level.txt
cam/builder/__init__.py
cam/builder/build.py
cam/builder/configuration.py
cam/builder/tool.py
cam/commands/__init__.py
cam/commands/build.py
cam/utils/__init__.py
cam/utils/console.py
cam/utils/download.py
cam/utils/git.py
cam/utils/shell.py
test/test_commands.py
test/test_console.py
test/test_enviroment.py
test/test_null.py
test/test_source.py
test/testutils.py